recommender/__init__.py
recommender/collab.py
recommender/content.py
recommender/popularity.py
recommender_blackboxes-0.0.2.dist-info/LICENSE
recommender_blackboxes-0.0.2.dist-info/METADATA
recommender_blackboxes-0.0.2.dist-info/WHEEL
recommender_blackboxes-0.0.2.dist-info/top_level.txt
recommender_blackboxes-0.0.2.dist-info/RECORD
