Metadata-Version: 2.1
Name: recommender-blackboxes
Version: 0.0.2
Summary: Easy to use Recommender system package
Home-page: UNKNOWN
Author-email: rp813149@gmail.com
License: UNKNOWN
Platform: UNKNOWN
Classifier: Programming Language :: Python :: 3
Classifier: Programming Language :: Python :: 3.8
Classifier: License :: OSI Approved :: GNU General Public License v3 or later (GPLv3+)
Classifier: Operating System :: POSIX :: Linux
Requires-Dist: numpy (>=1.18.5)
Requires-Dist: pandas (>=1.0.5)
Requires-Dist: scikit-learn (>=0.23.2)
Provides-Extra: dev
Requires-Dist: pytest (>=3.7) ; extra == 'dev'
